LICENSE
MANIFEST.in
setup.py
tests.py
scrubber/__init__.py
scrubber.egg-info/PKG-INFO
scrubber.egg-info/SOURCES.txt
scrubber.egg-info/dependency_links.txt
scrubber.egg-info/requires.txt
scrubber.egg-info/top_level.txt