Metadata-Version: 1.0
Name: scrubber
Version: 1.6.0
Summary: A whitelisting HTML sanitizer
Home-page: http://github.com/samuel/python-scrubber/tree/master
Author: Samuel Stauffer
Author-email: samuel@lefora.com
License: UNKNOWN
Platform: UNKNOWN
Classifier: Intended Audience :: Developers
Classifier: License :: OSI Approved :: BSD License
Classifier: Operating System :: OS Independent
Classifier: Programming Language :: Python
Classifier: Topic :: Software Development
Classifier: Topic :: Software Development :: Libraries
Classifier: Topic :: Software Development :: Libraries :: Python Modules
